tests/__init__.py
tests/performance_test.py
tests/test_cli.py
tests/test_oracle.py
tests/test_oracle_enhanced.py
web3_oracle/__init__.py
web3_oracle/cli.py
web3_oracle/oracle.py
web3_oracle/setup.py
web3_oracle/data/altcoins_prices.csv
web3_oracle/data/bitcoin_prices.csv
web3_oracle/data/btc_block_prices.csv
web3_oracle/data/eth_block_prices.csv
web3_oracle/data/ethereum_prices.csv
web3_oracle/data/stable_prices.csv
web3_oracle/data/token_addresses.csv
web3_oracle/tools/__init__.py
web3_oracle/tools/index_btc_blocks.py
web3_oracle/tools/index_eth_blocks.py
web3_oracle-0.2.0.dist-info/LICENSE
web3_oracle-0.2.0.dist-info/METADATA
web3_oracle-0.2.0.dist-info/WHEEL
web3_oracle-0.2.0.dist-info/entry_points.txt
web3_oracle-0.2.0.dist-info/top_level.txt
web3_oracle-0.2.0.dist-info/RECORD
