Metadata-Version: 2.1
Name: web3_oracle
Version: 0.2.0
Summary: A package to retrieve token prices by timestamp
Home-page: https://github.com/gmatrixuniverse/web3_oracle
Author: Gmatrixuniverse
Author-email: gmatrixuniverse@gmail.com
Classifier: Programming Language :: Python :: 3
Classifier: License :: OSI Approved :: MIT License
Classifier: Operating System :: OS Independent
Requires-Python: >=3.10
License-File: LICENSE
Requires-Dist: pandas
Requires-Dist: pytz
Requires-Dist: web3
